ab_core/template/__init__.py
ab_core/template/placeholder.py
ab_template_package-0.1.0.dist-info/METADATA
ab_template_package-0.1.0.dist-info/WHEEL
ab_template_package-0.1.0.dist-info/licenses/LICENSE
ab_template_package-0.1.0.dist-info/RECORD
